transfat/__init__.py
transfat/fatsort.py
transfat/main.py
transfat/rename.py
transfat/system.py
transfat/talk.py
transfat/transfer.py
transfat/version.py
transfat/config/__init__.py
transfat/config/config.ini
transfat/config/constants.py
transfat/config/rename_targets.py
transfat-0.3.0.1.dist-info/DESCRIPTION.rst
transfat-0.3.0.1.dist-info/METADATA
transfat-0.3.0.1.dist-info/RECORD
transfat-0.3.0.1.dist-info/WHEEL
transfat-0.3.0.1.dist-info/entry_points.txt
transfat-0.3.0.1.dist-info/metadata.json
transfat-0.3.0.1.dist-info/top_level.txt
usr/local/man/man1/transfat.1
