Metadata-Version: 2.0
Name: transfat
Version: 0.3.0.1
Summary: Play audio files on your car stereo and maintain sanity
Home-page: https://github.com/mwiens91/trans-fat
Author: Matt Wiens
Author-email: mwiens91@gmail.com
License: MIT
Platform: UNKNOWN
Classifier: Development Status :: 4 - Beta
Classifier: Intended Audience :: End Users/Desktop
Classifier: License :: OSI Approved :: MIT License
Classifier: Natural Language :: English
Classifier: Operating System :: Unix
Classifier: Programming Language :: Python :: 3 :: Only
